{
  "recentFiles": [
    {
      "basename": "103 Golang Index",
      "path": "100 study-notes/103 Golang/103 Golang Index.md"
    },
    {
      "basename": "Go - Channels",
      "path": "100 study-notes/103 Golang/Go - Channels.md"
    },
    {
      "basename": "Go - Select",
      "path": "100 study-notes/103 Golang/Go - Select.md"
    },
    {
      "basename": "Go - Buffered Channels",
      "path": "100 study-notes/103 Golang/Go - Buffered Channels.md"
    },
    {
      "basename": "106 Git Index",
      "path": "100 study-notes/106 Git/106 Git Index.md"
    },
    {
      "basename": "Git - Merging",
      "path": "100 study-notes/106 Git/Git - Merging.md"
    },
    {
      "basename": "Git - Branching, Rebasing & Merging",
      "path": "100 study-notes/106 Git/Git - Branching, Rebasing & Merging.md"
    },
    {
      "basename": "Git - Commands",
      "path": "100 study-notes/106 Git/Git - Commands.md"
    },
    {
      "basename": "Git - Cherrypicking",
      "path": "100 study-notes/106 Git/Git - Cherrypicking.md"
    },
    {
      "basename": "102 AWS DVA Index",
      "path": "100 study-notes/102 AWS DVA/102 AWS DVA Index.md"
    },
    {
      "basename": "Go - Concurrency",
      "path": "100 study-notes/103 Golang/Go - Concurrency.md"
    },
    {
      "basename": "Go - Slices",
      "path": "100 study-notes/103 Golang/Go - Slices.md"
    },
    {
      "basename": "Go - Slice Working",
      "path": "100 study-notes/103 Golang/Go - Slice Working.md"
    },
    {
      "basename": "Go - Race Conditions & Mutexes",
      "path": "100 study-notes/103 Golang/Go - Race Conditions & Mutexes.md"
    },
    {
      "basename": "Go - Structs",
      "path": "100 study-notes/103 Golang/Go - Structs.md"
    },
    {
      "basename": "Go - Interfaces",
      "path": "100 study-notes/103 Golang/Go - Interfaces.md"
    },
    {
      "basename": "AWS Storage Gateway",
      "path": "100 study-notes/101 AWS SAA/AWS Storage Gateway.md"
    },
    {
      "basename": "Aurora",
      "path": "100 study-notes/101 AWS SAA/Aurora.md"
    },
    {
      "basename": "IAM Basics",
      "path": "100 study-notes/101 AWS SAA/IAM Basics.md"
    },
    {
      "basename": "STS & Identity Federation",
      "path": "100 study-notes/101 AWS SAA/STS & Identity Federation.md"
    },
    {
      "basename": "101 AWS SAA Index",
      "path": "100 study-notes/101 AWS SAA/101 AWS SAA Index.md"
    },
    {
      "basename": "104 Linux Index",
      "path": "100 study-notes/104 Linux/104 Linux Index.md"
    },
    {
      "basename": "Linux - Xargs",
      "path": "100 study-notes/104 Linux/Linux - Xargs.md"
    },
    {
      "basename": "Git - Miscellaneous",
      "path": "100 study-notes/106 Git/Git - Miscellaneous.md"
    },
    {
      "basename": "Linux - Using fd",
      "path": "100 study-notes/104 Linux/Linux - Using fd.md"
    },
    {
      "basename": "obsidian tips and tricks",
      "path": "400 misc/obsidian tips and tricks.md"
    },
    {
      "basename": "note taking in obsidian",
      "path": "400 misc/note taking in obsidian.md"
    },
    {
      "basename": "projects",
      "path": "400 misc/projects.md"
    },
    {
      "basename": "300 home",
      "path": "300 short-notes/300 home.md"
    },
    {
      "basename": "200 home",
      "path": "200 general-notes/200 home.md"
    },
    {
      "basename": "100 home",
      "path": "100 study-notes/100 home.md"
    },
    {
      "basename": "000 home",
      "path": "000 home.md"
    },
    {
      "basename": "Git - Single Machine Multiple Accounts",
      "path": "100 study-notes/106 Git/Git - Single Machine Multiple Accounts.md"
    },
    {
      "basename": "API Gateway DVA",
      "path": "100 study-notes/102 AWS DVA/API Gateway DVA.md"
    },
    {
      "basename": "S3 Performance",
      "path": "100 study-notes/101 AWS SAA/S3 Performance.md"
    },
    {
      "basename": "DynamoDB Indexes",
      "path": "100 study-notes/102 AWS DVA/DynamoDB Indexes.md"
    },
    {
      "basename": "SQS DVA",
      "path": "100 study-notes/102 AWS DVA/SQS DVA.md"
    },
    {
      "basename": "SQS",
      "path": "100 study-notes/101 AWS SAA/SQS.md"
    },
    {
      "basename": "Go - Functions",
      "path": "100 study-notes/103 Golang/Go - Functions.md"
    },
    {
      "basename": "Go - Pointers",
      "path": "100 study-notes/103 Golang/Go - Pointers.md"
    },
    {
      "basename": "Go - Error Handling",
      "path": "100 study-notes/103 Golang/Go - Error Handling.md"
    },
    {
      "basename": "publish-obsidian-vault",
      "path": "400 misc/publish-obsidian-vault.md"
    },
    {
      "basename": "backup-obisidian-vault",
      "path": "400 misc/backup-obisidian-vault.md"
    },
    {
      "basename": "Git - Introduction",
      "path": "100 study-notes/106 Git/Git - Introduction.md"
    },
    {
      "basename": "How to setup neovim",
      "path": "300 short-notes/How to setup neovim.md"
    },
    {
      "basename": "Git - Reversing Changes",
      "path": "100 study-notes/106 Git/Git - Reversing Changes.md"
    },
    {
      "basename": "Git - Staging & Committing",
      "path": "100 study-notes/106 Git/Git - Staging & Committing.md"
    },
    {
      "basename": "Git - Relative Refs",
      "path": "100 study-notes/106 Git/Git - Relative Refs.md"
    },
    {
      "basename": "Git - Remote Repository",
      "path": "100 study-notes/106 Git/Git - Remote Repository.md"
    },
    {
      "basename": "Step Functions",
      "path": "100 study-notes/102 AWS DVA/Step Functions.md"
    }
  ],
  "omittedPaths": [],
  "maxLength": null
}